{
    "event": "2017",
    "owner_id": "197482",
    "members": {
        "197482": {
            "completion_day_level": {
                "1": {
                    "1": {
                        "get_star_ts": 1512214572
                    },
                    "2": {
                        "get_star_ts": 1512215148
                    }
                },
                "2": {
                    "1": {
                        "get_star_ts": 1512215922
                    },
                    "2": {
                        "get_star_ts": 1512217415
                    }
                },
                "3": {
                    "1": {
                        "get_star_ts": 1512386905
                    },
                    "2": {
                        "get_star_ts": 1512395305
                    }
                },
                "4": {
                    "1": {
                        "get_star_ts": 1512395825
                    },
                    "2": {
                        "get_star_ts": 1512397441
                    }
                },
                "5": {
                    "1": {
                        "get_star_ts": 1512457013
                    },
                    "2": {
                        "get_star_ts": 1512457232
                    }
                },
                "6": {
                    "1": {
                        "get_star_ts": 1512537853
                    },
                    "2": {
                        "get_star_ts": 1512538661
                    }
                },
                "7": {
                    "1": {
                        "get_star_ts": 1512630270
                    },
                    "2": {
                        "get_star_ts": 1512664485
                    }
                },
                "8": {
                    "1": {
                        "get_star_ts": 1512714222
                    },
                    "2": {
                        "get_star_ts": 1512714855
                    }
                },
                "9": {
                    "1": {
                        "get_star_ts": 1512804454
                    },
                    "2": {
                        "get_star_ts": 1512804989
                    }
                },
                "10": {
                    "1": {
                        "get_star_ts": 1512885635
                    },
                    "2": {
                        "get_star_ts": 1512892885
                    }
                },
                "11": {
                    "1": {
                        "get_star_ts": 1512970638
                    },
                    "2": {
                        "get_star_ts": 1512970889
                    }
                },
                "12": {
                    "1": {
                        "get_star_ts": 1513056637
                    },
                    "2": {
                        "get_star_ts": 1513057592
                    }
                },
                "13": {
                    "1": {
                        "get_star_ts": 1513143546
                    },
                    "2": {
                        "get_star_ts": 1513145689
                    }
                },
                "14": {
                    "1": {
                        "get_star_ts": 1513231215
                    },
                    "2": {
                        "get_star_ts": 1513238821
                    }
                },
                "15": {
                    "1": {
                        "get_star_ts": 1513317956
                    },
                    "2": {
                        "get_star_ts": 1513322512
                    }
                },
                "16": {
                    "1": {
                        "get_star_ts": 1513402610
                    },
                    "2": {
                        "get_star_ts": 1513407017
                    }
                },
                "17": {
                    "1": {
                        "get_star_ts": 1513491483
                    },
                    "2": {
                        "get_star_ts": 1513494135
                    }
                },
                "18": {
                    "1": {
                        "get_star_ts": 1513575983
                    },
                    "2": {
                        "get_star_ts": 1513585612
                    }
                },
                "19": {
                    "1": {
                        "get_star_ts": 1513666506
                    },
                    "2": {
                        "get_star_ts": 1513666733
                    }
                },
                "20": {
                    "1": {
                        "get_star_ts": 1513755399
                    },
                    "2": {
                        "get_star_ts": 1513756841
                    }
                },
                "21": {
                    "1": {
                        "get_star_ts": 1513856699
                    },
                    "2": {
                        "get_star_ts": 1513856730
                    }
                },
                "22": {
                    "1": {
                        "get_star_ts": 1513922290
                    },
                    "2": {
                        "get_star_ts": 1513928454
                    }
                },
                "23": {
                    "1": {
                        "get_star_ts": 1514013999
                    },
                    "2": {
                        "get_star_ts": 1514015185
                    }
                },
                "24": {
                    "1": {
                        "get_star_ts": 1514099642
                    },
                    "2": {
                        "get_star_ts": 1514099713
                    }
                },
                "25": {
                    "1": {
                        "get_star_ts": 1514182841
                    },
                    "2": {
                        "get_star_ts": 1514182933
                    }
                }
            },
            "stars": 50,
            "id": "197482",
            "local_score": 450,
            "global_score": 0,
            "last_star_ts": 1514182933,
            "name": "R Vaughan"
        },
        "440387": {
            "global_score": 0,
            "last_star_ts": 1545320471,
            "name": "handybitesize",
            "stars": 27,
            "completion_day_level": {
                "1": {
                    "1": {
                        "get_star_ts": 1543851088
                    },
                    "2": {
                        "get_star_ts": 1543851426
                    }
                },
                "2": {
                    "1": {
                        "get_star_ts": 1543851712
                    },
                    "2": {
                        "get_star_ts": 1543852038
                    }
                },
                "3": {
                    "1": {
                        "get_star_ts": 1543855781
                    },
                    "2": {
                        "get_star_ts": 1543931072
                    }
                },
                "4": {
                    "1": {
                        "get_star_ts": 1543931455
                    },
                    "2": {
                        "get_star_ts": 1543931597
                    }
                },
                "5": {
                    "1": {
                        "get_star_ts": 1543931998
                    },
                    "2": {
                        "get_star_ts": 1543932073
                    }
                },
                "6": {
                    "1": {
                        "get_star_ts": 1543935110
                    },
                    "2": {
                        "get_star_ts": 1543935240
                    }
                },
                "7": {
                    "1": {
                        "get_star_ts": 1543936527
                    },
                    "2": {
                        "get_star_ts": 1544017321
                    }
                },
                "8": {
                    "1": {
                        "get_star_ts": 1544018553
                    },
                    "2": {
                        "get_star_ts": 1544018634
                    }
                },
                "9": {
                    "1": {
                        "get_star_ts": 1544019873
                    },
                    "2": {
                        "get_star_ts": 1544020232
                    }
                },
                "10": {
                    "1": {
                        "get_star_ts": 1544545497
                    },
                    "2": {
                        "get_star_ts": 1545318548
                    }
                },
                "11": {
                    "1": {
                        "get_star_ts": 1544549827
                    }
                },
                "12": {
                    "1": {
                        "get_star_ts": 1544713134
                    },
                    "2": {
                        "get_star_ts": 1544713870
                    }
                },
                "13": {
                    "1": {
                        "get_star_ts": 1545305397
                    }
                },
                "14": {
                    "1": {
                        "get_star_ts": 1545320471
                    }
                },
                "24": {
                    "1": {
                        "get_star_ts": 1543842936
                    },
                    "2": {
                        "get_star_ts": 1543843961
                    }
                }
            },
            "local_score": 216,
            "id": "440387"
        },
        "491038": {
            "local_score": 0,
            "id": "491038",
            "completion_day_level": {},
            "stars": 0,
            "last_star_ts": "0",
            "name": "plod",
            "global_score": 0
        },
        "638560": {
            "global_score": 0,
            "name": "Toby Maxwell-Lyte",
            "last_star_ts": "0",
            "completion_day_level": {},
            "stars": 0,
            "id": "638560",
            "local_score": 0
        },
        "667949": {
            "stars": 0,
            "completion_day_level": {},
            "id": "667949",
            "local_score": 0,
            "global_score": 0,
            "name": "@cmjdiff",
            "last_star_ts": "0"
        },
        "696996": {
            "global_score": 0,
            "last_star_ts": "0",
            "name": "tomgallard",
            "completion_day_level": {},
            "stars": 0,
            "local_score": 0,
            "id": "696996"
        },
        "754943": {
            "global_score": 0,
            "name": "Gareth Hendry",
            "last_star_ts": "0",
            "completion_day_level": {},
            "stars": 0,
            "id": "754943",
            "local_score": 0
        },
        "758120": {
            "last_star_ts": "0",
            "name": "James Tancock",
            "global_score": 0,
            "local_score": 0,
            "id": "758120",
            "stars": 0,
            "completion_day_level": {}
        },
        "1177054": {
            "completion_day_level": {},
            "stars": 0,
            "local_score": 0,
            "id": "1177054",
            "global_score": 0,
            "last_star_ts": "0",
            "name": "wose2008"
        }
    }
}